Workbook

Sheet 销售成本
A1: 产品销售成本计算表
A2: 编制单位：揭阳市揭东区磐东洪运来机械厂 2025年12月 单位:元
A3: 品名 项目 | B3: 期初库存 | D3: 本期销售 | F3: 本期生产 | H3: 本月销售成本 | K3: 期末库存
B4: 数量 | C4: 金额 | D4: 数量 | E4: 金额 | F4: 数量 | G4: 金额 | H4: 数量 | I4: 单价 | J4: 金额 | K4: 数量 | L4: 金额 | N4: 销售单价 | R4: 报关 | S4: 数量 | T4: 金额 | U4: 订单 | V4: 成本
A5: 铁制导轨（千克 | B5: 80175.77 | C5: 575550.95 | D5: 80175.77 | E5: 617291.35 | F5: =S5 | G5: =E5/D5*D5*测算表!$G$25*0+V5 | H5: =D5 | I5: =(C5+G5)/(B5+F5) | J5: =H5*I5 | K5: =B5+F5-H5 | L5: =C5+G5-J5 | N5: =E6/D6 | R5: 铁制导轨（千克 | S5: 58351.29 | T5: 421616.79 | U5: -76-77 | V5: =T5*测算表!$G$25
A6: 导轨（套 | D6: 966 | E6: 5463.72 | F6: =D6-B6 | G6: =E6/D6*F6*测算表!$G$25 | H6: =D6 | I6: =(C6+G6)/(B6+F6) | J6: =H6*I6 | K6: =B6+F6-H6 | L6: =C6+G6-J6 | N6: =E7/D7
A7: 滑轨（付 | D7: 37360 | E7: 140194.16 | F7: =D7-B7 | G7: =E7/D7*F7*测算表!$G$25 | H7: =D7 | I7: =(C7+G7)/(B7+F7) | J7: =H7*I7 | K7: =B7+F7-H7 | L7: =C7+G7-J7 | N7: =E10/D10
A8: 滑轨（套 | D8: 16590 | E8: 79355.75 | F8: =D8-B8 | G8: =E8/D8*F8*测算表!$G$25 | H8: =D8 | I8: =(C8+G8)/(B8+F8) | J8: =H8*I8 | K8: =B8+F8-H8 | L8: =C8+G8-J8
S9: =SUM(S5:S8) | T9: =SUM(T5:T8) | U9: =T9/S9 | V9: =SUM(V5:V8)
A12: 合 计 | B12: =SUM(B5:B11) | C12: =SUM(C5:C11) | D12: =SUM(D5:D11) | E12: =SUM(E5:E11) | F12: =SUM(F5:F11) | G12: =SUM(G5:G11) | H12: =SUM(H5:H11) | J12: =SUM(J5:J11) | K12: =SUM(K5:K11) | L12: =SUM(L5:L11)
J14: =H10*I10
E17: =E6+E7

Sheet 产品成本
A1: 产 品 成 本 核 算 表
A2: 编制单位:揭阳市揭东区磐东洪运来机械厂 2025.12 单位:元
A3: 项目 品名 | B3: 总计金额 | C3: =销售成本!A5 | D3: =销售成本!A6 | E3: =销售成本!A7 | F3: =销售成本!A8 | L3: =生产成本月结表!J4 | M3: =生产成本月结表!E4-测算表!K7
A4: 一、直接计入 | B4: =B5+B7 | C4: =C5+C7 | D4: =D5+D7 | E4: =E5+E7 | F4: =F5+F7 | K4: =SUM(C4:I4)-B4 | L4: =生产成本月结表!J5
A5: 1.原材料 | B5: =B16-B8-B7 | C5: =B5/B16*C16 | D5: =C5/C16*D16 | E5: =D5/D16*E16 | F5: =E5/E16*F16 | K5: =SUM(C5:I5)-B5 | L5: =生产成本月结表!E6 | M5: 动力余额
A6: 2.包装物
A7: 3.工资及福利 | B7: =B16*0.10743 | C7: =B7/B16*C16 | D7: =C7/C16*D16 | E7: =D7/D16*E16 | F7: =E7/E16*F16 | K7: =SUM(C7:I7)-B7
A8: 二、分配计入 | B8: =B9+B10+B11+B13 | C8: =C9+C10+C11+C13 | D8: =D9+D10+D11+D13 | E8: =E9+E10+E11+E13 | F8: =F9+F10+F11+F13 | K8: =SUM(C8:I8)-B8 | O8: 加工费余额
A9: 1.水电费 | B9: =B16/54*电费!D64 | C9: =B9/B16*C16 | D9: =C9/C16*D16 | E9: =D9/D16*E16 | F9: =E9/E16*F16 | K9: =SUM(C9:I9)-B9 | O9: =-165188.19+0-B11
A10: 2.折旧费 | B10: =测算表!B9 | C10: =B10/B16*C16 | D10: =C10/C16*D16 | E10: =D10/D16*E16 | F10: =E10/E16*F16 | K10: =SUM(C10:I10)-B10
A11: 3.加工费 | B11: 203905 | C11: =B11/B16*C16 | D11: =C11/C16*D16 | E11: =D11/D16*E16 | F11: =E11/E16*F16 | K11: =SUM(C11:I11)-B11 | L11: =B5/材料!J5*P11 | O11: 90 | P11: =Q11/O11 | Q11: 63716.81
A12: 4.劳动保护费
A13: 5.物料费
A14: 6.燃油费 | M14: 成本率
A15: 7.其他费用 | L15: =生产成本月结表!H11 | M15: 材料接近0
A16: 总成本合计 | B16: =销售成本!G12 | C16: =销售成本!G5 | D16: =销售成本!G6 | E16: =销售成本!G7 | F16: =销售成本!G8 | K16: =SUM(C16:I16)-B16 | L16: =生产成本月结表!F20 | M16: 废料接近0 | N16: 废料太低（负数）降低加工费
A17: 单位 | C17: 千克 | D17: 套 | E17: 付 | F17: 套
A18: 产成品数量 | B18: =销售成本!F12 | C18: =销售成本!F5 | D18: =销售成本!F6 | E18: =销售成本!F7 | F18: =销售成本!F8 | K18: =SUM(C18:I18)-B18
A19: 平均单价 | C19: =C16/C18 | D19: =D16/D18 | E19: =E16/E18 | F19: =F16/F18
B22: =SUM(C22:F22) | C22: =C5/材料!$J$5*1000 | D22: =D5/材料!$J$5*1000 | E22: =E5/材料!$J$5*1000
C23: =C22-C18 | D23: =D22/D18 | E23: =E22/E18 | J23: 公斤
B24: =测算表!G25*产品成本!B25
A25: 料率 | B25: =B5/B16 | C25: 0.84093418
A26: 工资率 | B26: =B7/B16 | C26: 0.065046991
A27: 动力率 | B27: =B9/B16 | C27: 0.0157
A28: 加工 | B28: =B11/B16 | C28: 0.077704789 | D28: =产品成本!B16*0.042

Sheet 材料
A1: 原 材 料 进 销 存 月 结 表 | S1: =生产成本月结表!J4
A2: 编制单位：揭阳市揭东区磐东洪运来机械厂 2025 年 12 月份 单位：人民币元 | S2: =生产成本月结表!J5
A3: 品名 | B3: 单位 | C3: 上月结存 | F3: 本月进仓数 | I3: 本月发出数 | L3: 本月结余 | O3: 备注 | S3: =生产成本月结表!F20
C4: 数量 | D4: 单价 | E4: 金额 | F4: 数量 | G4: 单价 | H4: 金额 | I4: 数量 | J4: 单价 | K4: 金额 | L4: 数量 | M4: 单价 | N4: 金额
A5: 带钢 | B5: 吨 | F5: =14.2+18.23 | G5: =H5/F5 | H5: =49262.83+63242.48 | I5: 32.43 | J5: =(E5+H5)/(C5+F5) | K5: =I5*J5 | L5: =C5+F5-I5 | M5: =N5/L5 | N5: =E5+H5-K5 | Q5: =91.247-91.247 | R5: =S5/Q5 | S5: =380000-380000
A6: 冷轧带钢 | B6: 吨 | F6: =153.837+44.435 | G6: =H6/F6 | H6: =485337.17+137632.74 | I6: 119.5 | J6: =(E6+H6)/(C6+F6) | K6: =I6*J6 | L6: =C6+F6-I6 | M6: =N6/L6 | N6: =E6+H6-K6 | U6: =S1/J6
A7: 冷轧卷板 | B7: 吨 | C7: 77.517 | D7: =E7/C7 | E7: 245865.33 | I7: =C7 | J7: =(E7+H7)/(C7+F7) | K7: =I7*J7 | L7: =C7+F7-I7 | M7: =N7/L7 | N7: =E7+H7-K7
A8: 钢珠 | B8: 千克 | C8: 172.195 | D8: =E8/C8 | E8: 995.3 | F8: =6153.231 | G8: =H8/F8 | H8: =35394.69 | I8: 1610 | J8: =(E8+H8)/(C8+F8) | K8: =I8*J8 | L8: =C8+F8-I8 | M8: =N8/L8 | N8: =E8+H8-K8 | T8: 37.5
A9: 滑轨塑料配件 | B9: 套 | C9: 47181 | D9: =E9/C9 | E9: 22964.38 | F9: 45454 | G9: =H9/F9 | H9: 22123.89 | I9: 31720 | J9: =(E9+H9)/(C9+F9) | K9: =I9*J9 | L9: =C9+F9-I9 | M9: =N9/L9 | N9: =E9+H9-K9 | R9: 物料 | U9: =V9/J8 | V9: =产品成本!B16*0.05
A10: 润滑脂 | B10: 桶 | U10: =V10/J9 | V10: =产品成本!B16*0.03
A11: 纸箱 | B11: 个 | C11: 2263 | D11: =E11/C11 | E11: 6007.77 | F11: 6532 | G11: =H11/F11 | H11: 17341.59 | I11: 3500 | J11: =(E11+H11)/(C11+F11) | K11: =I11*J11 | L11: =C11+F11-I11 | M11: =N11/L11 | N11: =E11+H11-K11 | U11: =V11/J10 | V11: =产品成本!B16*0.02
A12: 卡板托盘 | B12: 套
A13: 胶带 | B13: 平方米
A14: 废料 | B14: 吨 | F14: 87.011315 | G14: =H14/F14 | H14: =210408.76/1.13*0.95502022 | L14: =C14+F14-I14 | M14: =N14/L14 | N14: =E14+H14-K14
A16: 合 计 | C16: =SUM(C5:C15) | E16: =SUM(E5:E15) | F16: =SUM(F5:F15) | H16: =SUM(H5:H15) | I16: =SUM(I5:I15) | K16: =SUM(K5:K15) | L16: =SUM(L5:L15) | N16: =SUM(N5:N15) | O16: =S5
J17: =SUM(K15:K15)/(SUM(I15:I15)+(I8+I6)/1000)
F18: 58369.933 | H18: 810335.39
F19: =F18-F16 | H19: =H18-H16
I20: =SUM(I5:I12) | J20: =K20/I20 | K20: =SUM(K5:K12) | N20: =测算表!G13/0.13-N16
I24: 钢珠 | J24: 0.015 | K24: =J24*产品成本!$B$16/J8
I25: 滑轨塑料配件 | J25: 0.025 | K25: =J25*产品成本!$B$16/J9
I26: 润滑脂 | J26: 0.007 | K26: =J26*产品成本!$B$16/J10
I27: 纸箱 | J27: 0.015 | K27: =J27*产品成本!$B$16/J11
I28: 卡板托盘 | J28: 0.02 | K28: =J28*产品成本!$B$16/J12

Sheet 测算表
A1: 销售废料0元 | E1: =B2+D4 | H1: 含税 | I1: 金额 | J1: 税额
A2: 收入 | B2: =销售成本!E12+H7 | G2: 冲减无票销售 | J2: =H2-I2 | K2: =H2/1.13
A3: 成本 | B3: =销售成本!J12+K7 | C3: 增值税 | D3: =(D4-F4-F5)
C4: 销项 | D4: 109499.64 | E4: 进项 | F4: =F13 | H4: =生产成本月结表!J4
A5: 生产成本 | B5: =B6+B7+B8 | E5: 留抵
A6: 1.材料 | B6: =产品成本!B5 | H6: 金额 | I6: 税额 | J6: 含税
A7: 1.工资 | B7: 75100 | E7: =生产成本月结表!J5 | G7: 废铁 | J7: =H7+I7 | K7: =废料!X119*0
A8: 3.制造费用 | B8: =B9+B10+B11 | G8: 开票销售 | J8: =H8+I8
A9: 3.1折旧 | B9: 3567.6 | D9: 期初电 | E9: 期末电 | G9: 无票销售 | H9: =H10-H7-H8 | I9: =I10-I7-I8 | J9: =J10-J7-J8
A10: 3.2电费 | B10: =电费!E64 | D10: =生产成本月结表!B6 | E10: =生产成本月结表!E6
A11: 3.3加工费 | B11: =产品成本!B11-生产成本月结表!B8
D12: 期初待抵 | E12: 本期增加 | F12: 本期认证 | G12: 期末留抵
A13: 主营业务税金及附加 | B13: =B14+B15+B16+B17 | D13: 89965.29 | E13: =E14+1088.48+68.72+103.08 | F13: 93998.6 | G13: =D13+E13-F13
A14: 1.城建税 | B14: =D3*0.07/2-0.01 | E14: 105343.61
A15: 2.教育费附加 | B15: =IF(B2<100000,0,D3*0.03/2)-0.01 | G15: 102570.58 | H15: =G13-G15
A16: 3.地方教育费附加 | B16: =IF(B2<100000,0,D3*0.02/2)
D17: 年销售额 | E17: =E28/12*12
A18: 销售费用 | B18: =SUM(B19:B21) | D18: 年利润总额 | E18: 222369.28
A19: 出口服务费 | B19: 1908 | D19: 投资者减除
A20: 报关费 | B20: =721+1884.9 | D20: 应纳税所得额 | E20: =E18-E19
A21: 运输费 | B21: =6872+10308 | D21: 应纳税额 | E21: =IF(E20<=30000,E20*0.05,IF(E20<=90000,E20*0.1-1500,IF(E20<=300000,E20*0.2-10500,IF(E20<=500000,E20*0.3-40500,E20*0.35-65500))))
D22: 减免税额 | E22: =E21/2 | F22: =E22/E17 | G22: =E17*0.00206870879425307-E22
A23: 营业利润 | B23: =B2-B3-B13-B18 | D23: 已缴纳税额 | E23: =1366.83+2284.43+5819.66
D24: 缓交税额
A25: 管理费用 | B25: =SUM(B26:B35) | D25: 应补税额 | E25: =E21-E22-E23-E24 | G25: 0.99385816
A26: 1.工资 | B26: 5000 | I26: 税款
A27: 2.办公 | I27: =D3+B14+B15+B16+B35+E38
A28: 3.差旅 | D28: 累计销售额 | E28: =生产成本月结表!B14
A29: 4.业务 | D29: 利润总额 | E29: =E18/12*12
A30: 5.保险 | D30: 实际利润总额 | E30: =203838.52+B47 | G30: =E28-E30
A31: 6.折旧 | D31: 差异 | E31: =E30-E29
A32: 7.福利费 | D32: 投资者减除
A33: 8.土地使用税 | C33: 7500 | D33: 应纳税所得额 | E33: =E30-E32
A34: 9.房产税 | C34: 3746.4 | D34: 应纳税额 | E34: =IF(E33<=30000,E33*0.05,IF(E33<=90000,E33*0.1-1500,IF(E33<=300000,E33*0.2-10500,IF(E33<=500000,E33*0.3-40500,E33*0.35-65500))))
A35: 10.社保费 | B35: 8623.65 | D35: 减免税额 | E35: =E34/2 | F35: =E35/E28
D36: 已缴纳税额 | E36: =E23
A37: 财务费用 | B37: =B39-B38+B40+B41-B42 | D37: 缓交税额 | E37: =E24
A38: 利息 | B38: 50.08 | D38: 应补税额 | E38: =E34-E35-E36-E37
A39: 手续费 | B39: =2.5+94.5+10 | E39: =E25-E38
A40: 贷款息 | B40: 3150
A41: 退税综合服务费
A42: 汇兑损益 | B42: =14957.69
A44: 营业外收入
A45: 营业外支出 | B45: =10.39
A47: 利润总额 | B47: =B23-B25-B37+B44-B45
A49: 净利润 | B49: =B47

Sheet 工资
A1: 揭阳市揭东区磐东洪运来机械厂
A2: 2025年12月工资计算表
B3: 货币单位:元
A4: 部门名称 | B4: 应发金额
A5: 生产车间 | B5: =测算表!B7
A6: 管理部门 | B6: =测算表!B26
A7: 合 计 | B7: =B5+B6
B11: =B5/4500

Sheet 生产成本月结表
A1: 生产成本月结表
A2: 编制单位：揭阳市揭东区磐东洪运来机械厂 2025 年 12 月份 单位：元
A3: 项目 | B3: 上月结存 | C3: 本月发生 | D3: 本月结转 | E3: 本月结余 | F3: 备注
A4: 材料费 | B4: 177431.24 | C4: =材料!K16-材料!S9 | D4: =产品成本!B5+测算表!K7+材料!H14 | E4: =B4+C4-D4 | F4: =E4/E9 | G4: =产品成本!B25 | J4: =E6/(G6/G4)-E4
A5: 工资 | B5: 26088.3 | C5: =测算表!B7 | D5: =产品成本!B7 | E5: =B5+C5-D5 | F5: =E5/E9 | G5: =产品成本!B26 | J5: =E6/(G6/G5)-E5
A6: 动力 | B6: 2376.3 | C6: =测算表!B10 | D6: =产品成本!B9 | E6: =B6+C6-D6 | F6: =E6/E9 | G6: =产品成本!B27
A7: 折旧 | C7: =测算表!B9 | D7: =产品成本!B10
A8: 加工 | C8: =测算表!B11 | D8: =产品成本!B11
A9: 合 计 | B9: =SUM(B4:B8) | C9: =SUM(C4:C8) | D9: =SUM(D4:D8) | E9: =SUM(E4:E8)
H11: =G12-H12
G12: =E4+材料!N16 | H12: =F14*产品成本!B24
E13: =E9+材料!N16+销售成本!L12*0
A14: 累计销售额 | B14: =7527087+测算表!B2 | D14: =材料!O16 | E14: =E13/0.71947*0.13 | F14: =E14/0.13 | G14: =F14*C15
A15: 实缴 | B15: =169486.28+测算表!D3 | C15: =B15/B14 | D15: =D14*0.13 | E15: =测算表!G13
A16: 应缴 | B16: =B14*0.0221 | E16: =E14-E15
A17: 多交 | B17: =B15-B16
H18: =H11-F20
D19: =E16-D15
E20: =G14-B17-D19 | F20: =E20/0.13 | G20: 少结材料 | H20: 开票单价提高
G21: 废料

Sheet 付工资
A1: 揭阳市揭东区磐东洪运来机械厂
A2: 工 资 表
E4: 单位：元 2025年11月
A6: 序号 | B6: 姓 名 | C6: 应发工资 | D6: 扣 款 | E6: 实发工资 | F6: 签 名 | J6: 姓名 | M6: 姓 名 | N6: 应发工资
B7: 李洪军 | C7: 2800 | D7: 0 | E7: =C7-D7 | I7: 1 | J7: 李洪军 | M7: 曾小琼 | N7: 6550
B8: 李静 | C8: 2200 | D8: 0 | E8: =C8-D8 | I8: 2 | J8: 李静 | M8: 陈云凤 | N8: 8840
B9: 杨泽明 | C9: 8840 | D9: 0 | E9: =C9-D9 | H9: =C9-1000 | I9: 3 | J9: 杨泽明 | M9: 代飞 | N9: 6270
B10: 余文平 | C10: 8080 | D10: 0 | E10: =C10-D10 | H10: =C10-1000 | I10: 4 | J10: 余文平 | M10: 代燕 | N10: 7470
B11: 陈云凤 | C11: 8840 | D11: 0 | E11: =C11-D11 | H11: =C11-1000 | I11: 5 | J11: 陈云凤 | M11: 代玉金 | N11: 8970
B12: 代玉金 | C12: 8970 | D12: 0 | E12: =C12-D12 | H12: =C12-1000 | I12: 6 | J12: 代玉金 | M12: 郭聪 | N12: 7750
B13: 杨艳群 | C13: 8860 | D13: 0 | E13: =C13-D13 | H13: =C13-1000 | I13: 7 | J13: 杨艳群 | M13: 李洪军 | N13: 2800
B14: 李金容 | C14: 7940 | D14: 0 | E14: =C14-D14 | H14: =C14-1000 | I14: 8 | J14: 李金容 | M14: 李金容 | N14: 7940
B15: 张贵华 | C15: 7680 | D15: 0 | E15: =C15-D15 | H15: =C15-1000 | I15: 9 | J15: 张贵华 | M15: 李静 | N15: 2200
B16: 王彬 | C16: 7320 | D16: 0 | E16: =C16-D16 | H16: =C16-1000 | I16: 10 | J16: 王彬 | M16: 刘华清 | N16: 6310
B17: 代燕 | C17: 7470 | D17: 0 | E17: =C17-D17 | H17: =C17-1000 | I17: 11 | J17: 代燕 | M17: 石光成 | N17: 6920
B18: 郭聪 | C18: 7750 | D18: 0 | E18: =C18-D18 | H18: =C18-1000 | I18: 12 | J18: 郭聪 | M18: 王彬 | N18: 7320
B19: 吴文荣 | C19: 7380 | D19: 0 | E19: =C19-D19 | H19: =C19-1000 | I19: 13 | J19: 吴文荣 | M19: 吴文荣 | N19: 7380
B20: 石光成 | C20: =7820-900 | D20: 0 | E20: =C20-D20 | H20: =C20-1000 | I20: 14 | J20: 石光成 | M20: 杨艳群 | N20: 8860
B21: 曾小琼 | C21: 6550 | D21: 0 | E21: =C21-D21 | H21: =C21-1000 | I21: 15 | J21: 曾小琼 | M21: 杨泽明 | N21: 8840
B22: 叶书香 | C22: 6560 | D22: 0 | E22: =C22-D22 | H22: =C22-1000 | I22: 16 | J22: 叶书香 | M22: 叶书香 | N22: 6560
B23: 代飞 | C23: 6270 | D23: 0 | E23: =C23-D23 | H23: =C23-1000 | I23: 17 | J23: 代飞 | M23: 余文平 | N23: 8080
B24: 刘华清 | C24: 6310 | D24: 0 | E24: =C24-D24 | H24: =C24-1000 | I24: 18 | J24: 刘华清 | M24: 张贵华 | N24: 7680
I25: 19 | J25: 谢苏玲
I26: 20 | J26: 钟玉婷
J27: 郑华强
J28: 郑文益
A29: 合 计 | C29: =SUM(C7:C28) | D29: =SUM(D7:D28) | E29: =SUM(E7:E28) | J29: 杨玲
J30: 杨玉银
C31: =126740-C29 | J31: 石珠福

Sheet 电费
B3: 2022年洪运来电费
B4: 月份 | C4: 度数（KWH） | D4: 单价 | E4: 金额（不含税 | F4: 税额 | G4: 金额（含税
B5: 1 | C5: 5962 | D5: =E5/C5 | E5: 4680 | G5: =E5+F5
B6: 2 | C6: 8344 | D6: =E6/C6 | E6: 6550 | G6: =E6+F6
B7: 3 | C7: 17771 | D7: =E7/C7 | E7: 13950 | G7: =E7+F7
B8: 4 | C8: 6408 | D8: =E8/C8 | E8: 5030 | G8: =E8+F8
B9: 5 | C9: 6268 | D9: =E9/C9 | E9: 4920 | G9: =E9+F9
B10: 6 | C10: 19465 | D10: =E10/C10 | E10: 15280 | G10: =E10+F10
B11: 7 | C11: 16917 | D11: =E11/C11 | E11: 13280 | G11: =E11+F11
B12: 8 | C12: 22739 | D12: =E12/C12 | E12: 17850 | G12: =E12+F12
B13: 9 | C13: 20280 | D13: =E13/C13 | E13: 15920 | G13: =E13+F13
B14: 10 | C14: 12637 | D14: =E14/C14 | E14: 9920 | G14: =E14+F14
A15: 付10月电费 | B15: 11 | C15: 22395 | D15: =E15/C15 | E15: 17580 | G15: =E15+F15
A16: 付11月电费 | B16: 12 | C16: 22624 | D16: =E16/C16 | E16: 17760 | G16: =E16+F16
C17: =SUM(C5:C16) | D17: =E17/C17 | E17: =SUM(E5:E16) | F17: =SUM(F5:F16) | G17: =SUM(G5:G16)
B19: 2023年洪运来电费
B20: 月份 | C20: 度数（KWH） | D20: 单价 | E20: 金额（不含税 | F20: 税额 | G20: 金额（含税
A21: 付12月电费 | B21: 1 | C21: 13452 | D21: =E21/C21 | E21: 10560 | G21: =E21+F21
A22: 付1月电费 | B22: 2 | C22: 12076 | D22: =E22/C22 | E22: 9480 | G22: =E22+F22
A23: 付2月电费 | B23: 3 | C23: 7465 | D23: =E23/C23 | E23: 5860 | G23: =E23+F23
A24: 付3月电费 | B24: 4 | C24: 27322 | D24: =E24/C24 | E24: 23920 | G24: =E24+F24
A25: 付4月电费 | B25: 5 | C25: 9580 | D25: =E25/C25 | E25: 9772 | G25: =E25+F25
A26: 付5月电费 | B26: 6 | C26: 17245 | D26: =E26/C26 | E26: 17590 | G26: =E26+F26
A27: 付6月电费 | B27: 7 | C27: 8108 | D27: =E27/C27 | E27: 8270 | G27: =E27+F27
A28: 付7月电费 | B28: 8 | C28: 5716 | D28: =E28/C28 | E28: 5830 | G28: =E28+F28
A29: 付8月电费 | B29: 9 | C29: 8657 | D29: =E29/C29 | E29: 8830 | G29: =E29+F29
A30: 付9月电费 | B30: 10 | C30: 6152 | D30: =E30/C30 | E30: 6275 | G30: =E30+F30
A31: 付10月电费 | B31: 11 | C31: 6647 | D31: =E31/C31 | E31: 6780 | G31: =E31+F31 | I31: 3693.6 | J31: =K31/I31 | K31: 2667.77
A32: 付11月电费 | B32: 12 | C32: 6398 | D32: =E32/C32 | E32: 6525.96 | G32: =E32+F32 | I32: 14638.8 | J32: =K32/I32 | K32: 10559.97
C33: =SUM(C21:C32) | D33: =E33/C33 | E33: =SUM(E21:E32) | F33: =SUM(F21:F32) | G33: =SUM(G21:G32) | L33: 当月月头
L34: 揭阳市揭东区磐东洪运来机械厂
B35: 2024年洪运来电费 | L35: 上月电费 度*0.785元/度=
B36: 月份 | C36: 度数（KWH） | D36: 单价 | E36: 金额（不含税 | F36: 税额 | G36: 金额（含税 | M36: 李
A37: 付12月电费 | B37: 1 | C37: 19500 | D37: =E37/C37 | E37: 14296.79 | G37: =E37+F37 | I37: =C37*50
A38: 付1月电费 | B38: 2 | C38: 13535.6 | D38: =E38/C38 | E38: 8560.59 | F38: 1112.88 | G38: =E38+F38 | I38: =C38*50
A39: 付2月电费 | B39: 3 | C39: 2168 | D39: =E39/C39 | E39: 1406.83 | F39: 182.89 | G39: =E39+F39 | I39: =C39*50
A40: 付3月电费 | B40: 4 | C40: 15748 | D40: =E40/C40 | E40: 10058.77 | F40: 1307.64 | G40: =E40+F40 | I40: =C40*50
A41: 付4月电费 | B41: 5 | C41: 15079.6 | D41: =E41/C41 | E41: 9633.17 | F41: 1252.31 | G41: =E41+F41 | I41: =C41*50
A42: 付5月电费 | B42: 6 | C42: 15882.8 | D42: =E42/C42 | E42: 10147.67 | F42: 1319.2 | G42: =E42+F42 | I42: =C42*50
A43: 付6月电费 | B43: 7 | C43: 12502.8 | D43: =E43/C43 | E43: 7645.17 | F43: 993.87 | G43: =E43+F43 | I43: =C43*50
A44: 付7月电费 | B44: 8 | C44: 14659.2 | D44: =E44/C44 | E44: 9001.38 | F44: 1170.18 | G44: =E44+F44 | I44: =C44*50
A45: 付8月电费 | B45: 9 | C45: 15394.4 | D45: =E45/C45 | E45: 9669.43 | F45: 1257.03 | G45: =E45+F45 | I45: =C45*50
A46: 付9月电费 | B46: 10 | C46: 13717.6 | D46: =E46/C46 | E46: 8632 | F46: 1122.16 | G46: =E46+F46 | I46: =C46*50
A47: 付10月电费 | B47: 11 | C47: 14601.6 | D47: =E47/C47 | E47: 9234.79 | F47: 1200.52 | G47: =E47+F47 | I47: =C47*50
A48: 付11月电费 | B48: 12 | C48: 13686.8 | D48: =E48/C48 | E48: 8508.45 | F48: 1106.1 | G48: =E48+F48 | I48: =C48*50
C49: =SUM(C37:C48) | D49: =E49/C49 | E49: =SUM(E37:E48) | F49: =SUM(F37:F48) | G49: =SUM(G37:G48) | I49: =SUM(I37:I48) | J49: 9028864.5 | K49: =J49/C49
B51: 2025年洪运来电费
B52: 月份 | C52: 度数（KWH） | D52: 单价 | E52: 金额（不含税 | F52: 税额 | G52: 金额（含税
A53: 付12月电费 | B53: 1 | C53: 14585.2 | D53: =E53/C53 | E53: 9216.66 | F53: 1198.17 | G53: =E53+F53 | I53: =C53*50
A54: 付1月电费 | B54: 2 | C54: 9111.2 | D54: =E54/C54 | E54: 5804.31 | F54: 754.56 | G54: =E54+F54 | I54: =C54*50
A55: 付2月电费 | B55: 3 | C55: 6703.6 | D55: =E55/C55 | E55: 4337.58 | F55: 563.89 | G55: =E55+F55 | I55: =C55*50
A56: 付3月电费 | B56: 4 | C56: 16442 | D56: =E56/C56 | E56: 10280.88 | F56: 1336.52 | G56: =E56+F56 | I56: =C56*50
A57: 付4月电费 | B57: 5 | C57: 14260 | D57: =E57/C57 | E57: 8929.14 | F57: 1160.79 | G57: =E57+F57 | I57: =C57*50
A58: 付5月电费 | B58: 6 | C58: 12711.6 | D58: =E58/C58 | E58: 8158.7 | F58: 1060.63 | G58: =E58+F58 | I58: =C58*50
A59: 付6月电费 | B59: 7 | C59: 14099.6 | D59: =E59/C59 | E59: 8740.11 | F59: 1136.21 | G59: =E59+F59 | I59: =C59*50
A60: 付7月电费 | B60: 8 | C60: 12654 | D60: =E60/C60 | E60: 7622.28 | F60: 990.9 | G60: =E60+F60 | I60: =C60*50
A61: 付8月电费 | B61: 9 | C61: 14051.2 | D61: =E61/C61 | E61: 8759.85 | F61: 1138.78 | G61: =E61+F61 | I61: =C61*50
A62: 付9月电费 | B62: 10 | C62: 13541.2 | D62: =E62/C62 | E62: 8621.66 | F62: 1120.82 | G62: =E62+F62 | I62: =C62*50
A63: 付10月电费 | B63: 11 | C63: 14225.6 | D63: =E63/C63 | E63: 9054.9 | F63: 1177.14 | G63: =E63+F63 | I63: =C63*50
A64: 付11月电费 | B64: 12 | C64: 13584.8 | D64: =E64/C64 | E64: 8372.91 | F64: 1088.48 | G64: =E64+F64 | I64: =C64*50
C65: =SUM(C53:C64) | D65: =E65/C65 | E65: =SUM(E53:E64) | F65: =SUM(F53:F64) | G65: =SUM(G53:G64) | I65: =SUM(I53:I64) | J65: 8369392 | K65: =J65/C65

Sheet 废料
B2: 品名 | C2: 单位 | D2: 上月结存 | G2: 本月进仓数 | J2: 本月发出数 | M2: 本月结余 | P2: 备注
D3: 数量 | E3: 单价 | F3: 金额 | G3: 数量 | H3: 单价 | I3: 金额 | J3: 数量 | K3: 单价 | L3: 金额 | M3: 数量 | N3: 单价 | O3: 金额
B4: 带钢 | C4: 吨 | D4: 89.063 | E4: 3913.4375 | F4: 348542.48 | G4: 178.262 | H4: 3720.7936 | I4: 663276.11 | J4: 180.64 | K4: 3784.9756 | L4: 683717.98 | M4: 86.685 | N4: 3784.9756 | O4: 328100.61 | P4: 5月
B5: 镀铝锌卷板 | C5: 吨 | G5: 7.745 | H5: 4010.581 | I5: 31061.95 | J5: 7.745 | K5: 4010.581 | L5: 31061.95 | M5: 0 | N5: #DIV/0! | O5: 0 | P5: 5月
J12: =SUM(J4:J7) | K12: =L12/J12 | L12: =SUM(L4:L7) | O12: =测算表!H20/0.13-O8
J13: =J12*0.09 | K13: 2930 | L13: =J13*K13
I17: 废料销售 | J17: 7 | K17: 2700 | L17: 18900 | M17: 4月未销售废料
I18: 废料销售 | J18: 18.5 | K18: 2886.0503 | L18: 53391.93 | M18: 5月未销售废料
I19: 废料销售 | J19: 3.375 | K19: 2834.9778 | L19: 9568.0502 | M19: 6月未销售废料
I20: 废料销售 | J20: 1.7919 | K20: 2834.9778 | L20: 5079.9968 | M20: 7月未销售废料
I21: 废料销售 | J21: 6.42321 | K21: 2834.9778 | L21: 18209.66 | M21: 8月未销售废料
I22: 废料销售 | J22: 10.06848 | K22: =L22/J22 | L22: 28543.92 | M22: 9月未销售废料
I23: 废料销售 | J23: 10.22121 | K23: 2834.9778 | L23: 28976.9 | M23: 10月未销售废料
I24: 废料销售 | J24: 16.785 | K24: =L24/J24 | L24: 47585.11 | M24: 11月未销售废料
I25: 废料销售 | J25: 19.075 | K25: =L25/J25 | L25: 62937.05 | M25: 12月未销售废料
J27: =SUM(J17:J26) | K27: =2930 | L27: =SUM(L17:L26) | N27: =L27/1.13 | O27: =生产成本月结表!F11
L28: =J27*K27-L17-L18-L19-L20-L21-L22-L23-L24 | O28: =N27-O27
J30: 85.324 | K30: =L30/J30 | L30: 250000 | N30: =L30/1.13
I31: 废料销售 | J31: =J27-J30 | K31: =L31/J31 | L31: =L27-L30 | M31: 12月未销售废料 | N31: =L31/1.13 | O31: =N31*0.964963653865046
I32: 废料销售 | J32: 16.84593 | K32: =L32/J32 | L32: 49358.575 | M32: 1月未销售废料 | N32: =L32/1.13 | O32: =N32*0.964963653865046
I33: 废料销售 | J33: 10.01151 | K33: =L33/J33 | L33: =29333.7243+0.68 | M33: 2月未销售废料 | N33: =L33/1.13 | O33: =N33*0.964963653865046
I34: 废料销售 | J34: 9.83223 | K34: 2930 | L34: 28808.434 | M34: 3月未销售废料 | N34: =L34/1.13 | O34: =N34*0.964963653865046
I35: 废料销售 | J35: 6.52545 | K35: 2930 | L35: 19119.569 | M35: 4月未销售废料 | N35: =L35/1.13 | O35: =N35*0.964963653865046
I36: 废料销售 | J36: 16.95465 | K36: 2930 | L36: 49677.124 | M36: 5月未销售废料 | N36: =L36/1.13 | O36: =N36*0.964963653865046
J39: =SUM(J31:J38) | K39: 2930 | L39: =SUM(L31:L38) | N39: =SUM(N31:N38) | O39: =SUM(O31:O38)
L40: =J39*K39-L31-L32-L33-L34-L35 | O40: =N39-O39
I42: 预测废料 | J42: =J27-J30+J39 | K42: =L42/J42 | L42: =L27-L30+L39
R45: 以上废料已结算
U47: 数量 | V47: 单价 | W47: 金额 | X47: 税额 | Y47: 含税金额
B48: 品名 | C48: 单位 | D48: 上月结存 | G48: 本月进仓数 | J48: 本月发出数 | M48: 本月结余 | P48: 备注 | R48: 45467 | S48: *金属制品*废铁 | T48: 吨 | U48: 68.259 | V48: =W48/U48 | W48: 176991.15 | X48: 23008.85 | Y48: 200000
D49: 数量 | E49: 单价 | F49: 金额 | G49: 数量 | H49: 单价 | I49: 金额 | J49: 数量 | K49: 单价 | L49: 金额 | M49: 数量 | N49: 单价 | O49: 金额 | V49: =Y48/U48
B50: 带钢 | C50: 吨 | D50: 86.685 | E50: 3784.9756 | F50: 328100.61 | G50: 75.48 | H50: 3820.2349 | I50: 288351.33 | J50: 102.786 | K50: 3801.3871 | L50: 390729.38 | M50: 59.379 | N50: 3801.3871 | O50: 225722.56 | P50: 6月
B51: 镀锌带钢 | C51: 吨 | G51: 8.234 | H51: 4309.7802 | I51: 35486.73 | J51: 8.234 | K51: 4309.7802 | L51: 35486.73 | M51: 0 | N51: #DIV/0! | O51: 0 | P51: 6月
B52: 带钢 | C52: 吨 | D52: 59.379 | E52: 3801.387 | F52: 225722.56 | G52: 259.376 | H52: 3828.8215 | I52: 993104.41 | J52: 79 | K52: 3823.7109 | L52: 302073.16 | M52: 239.755 | N52: 3823.7109 | O52: 916753.81 | P52: 7月
B53: 带钢 | C53: 吨 | D53: 239.755 | E53: 3823.7109 | F53: 916753.81 | G53: 104.677 | H53: 3678.9109 | I53: 385097.36 | J53: 106.6 | K53: 3779.7045 | L53: 402916.5 | M53: 237.832 | N53: 3779.7045 | O53: 898934.67 | P53: 8月
B54: 镀锌带钢 | C54: 吨 | D54: 9.086 | E54: 4310.044 | F54: 39161.06 | J54: 9.086 | K54: 4310.044 | L54: 39161.06 | M54: 0 | N54: #DIV/0! | O54: 0 | P54: 8月
B55: 冷轧板卷 | C55: 吨 | D55: 10.448 | E55: 3913.0159 | F55: 40883.19 | J55: 10.448 | K55: 3913.0159 | L55: 40883.19 | M55: 0 | N55: #DIV/0! | O55: 0 | P55: 8月 | R55: 2024.10.26 | S55: *金属制品*废铁 | T55: 吨 | U55: 11.54 | V55: =W55/U55 | W55: 26548.67 | X55: 3451.33 | Y55: 30000
B56: 带钢 | C56: 吨 | D56: 237.832 | E56: 3779.7045 | F56: 898934.67 | G56: 56.07 | H56: 3650.7621 | I56: 204698.23 | J56: 154.8 | K56: 3755.1051 | L56: 581290.27 | M56: 139.102 | N56: 3755.1051 | O56: 522342.63 | P56: 9月 | V56: =Y55/U55 | W56: =W55/N65*O65
G63: =K64*1.13
G64: =K65/G63 | J64: =SUM(J50:J59) | K64: =L64/J64 | L64: =SUM(L50:L59)
J65: =J64*0.09 | K65: 2930 | L65: =J65*K65 | N65: =L65/1.13 | O65: =N65*0.964963653865046
G66: =V56/G63 | O66: =N65-O65
I67: 预测废料 | J67: =J42-U48+J65 | K67: =L67/J67 | L67: =L42-Y48+L65
R69: 以上废料已结算
U71: 数量 | V71: 单价 | W71: 金额 | X71: 税额 | Y71: 含税金额
B72: 品名 | C72: 单位 | D72: 上月结存 | G72: 本月进仓数 | J72: 本月发出数 | M72: 本月结余 | P72: 备注 | R72: 2024.12.27 | S72: *金属制品*废铁 | T72: 吨 | U72: 39.684 | V72: =W72/U72 | W72: 88495.58 | X72: 11504.42 | Y72: 100000
D73: 数量 | E73: 单价 | F73: 金额 | G73: 数量 | H73: 单价 | I73: 金额 | J73: 数量 | K73: 单价 | L73: 金额 | M73: 数量 | N73: 单价 | O73: 金额 | R73: 2024.12.27 | S73: *金属制品*废铁 | T73: 吨 | U73: 19.842 | V73: =W73/U73 | W73: 44247.79 | X73: 5752.21 | Y73: 50000
B74: 带钢 | C74: 吨 | D74: 139.102 | E74: 3755.1051 | F74: 522342.63 | G74: 83.157 | H74: 3527.8189 | I74: 293362.84 | J74: 147.2 | K74: 3670.0672 | L74: 540233.89 | M74: 75.059 | N74: 3670.0672 | O74: 275471.58 | P74: 10月 | U74: 59.526 | V74: =W74/U74 | W74: 132743.37 | X74: =SUM(X72:X73) | Y74: =SUM(Y72:Y73)
B75: 带钢 | C75: 吨 | D75: 75.059 | E75: 3670.0673 | F75: 275471.58 | G75: 91.527 | H75: 3343.9332 | I75: 306060.17 | J75: 151.8 | K75: 3490.8801 | L75: 529915.6 | M75: 14.786 | N75: 3490.8801 | O75: 51616.153 | P75: 11月
B76: 镀锌带钢 | C76: 吨 | G76: 10.537 | H76: 3787.7479 | I76: 39911.5 | J76: 10.537 | K76: 3787.7479 | L76: 39911.5 | M76: 0 | N76: #DIV/0! | O76: 0 | P76: 11月 | V76: =Y74/U74
W78: =W74/1.13 | X78: =W78*0.984963653865046
X79: =W78-X78
J80: =SUM(J74:J78) | K80: =L80/J80 | L80: =SUM(L74:L78)
G81: =K80*1.13 | J81: =J80*0.09 | K81: 2519.91 | L81: =J81*K81 | N81: =L81/1.13 | O81: =N81*0.964963653865046
O82: =N81-O81
G83: =K84/G81 | I83: 预测废料 | J83: =J67-U55+J81 | K83: =L83/J83 | L83: =L65-Y55+L81
K84: 2519.91 | L84: =J83*K84
R87: 以上废料已结算
U90: 数量 | V90: 单价 | W90: 金额 | X90: 税额 | Y90: 含税金额
B91: 品名 | C91: 单位 | D91: 上月结存 | G91: 本月进仓数 | J91: 本月发出数 | M91: 本月结余 | P91: 备注 | R91: 2025.02.26 | S91: *金属制品*废铁 | T91: 吨 | U91: 36.535 | V91: =W91/U91 | W91: 79646.02 | X91: 10353.98 | Y91: 90000
D92: 数量 | E92: 单价 | F92: 金额 | G92: 数量 | H92: 单价 | I92: 金额 | J92: 数量 | K92: 单价 | L92: 金额 | M92: 数量 | N92: 单价 | O92: 金额
B93: 带钢 | C93: 吨 | D93: 14.786 | E93: 3490.8799 | F93: 51616.15 | G93: 202.971 | H93: 3581.4524 | I93: 726930.98 | J93: 127.2 | K93: 3575.3024 | L93: 454778.47 | M93: 90.557 | N93: 3575.3024 | O93: 323768.66 | P93: 12月
B94: 镀锌卷板 | C94: 吨 | G94: 12.733 | H94: 3885.1041 | I94: 49469.03 | J94: 12.733 | K94: 3885.1041 | L94: 49469.03 | M94: 0 | N94: #DIV/0! | O94: 0 | P94: 12月 | W94: =W91 | X94: =W94*测算表!G25
B95: 带钢 | C95: 吨 | D95: 90.557 | E95: 3575.3024 | F95: 323768.66 | G95: 86.292 | H95: 3811.9901 | I95: 328944.25 | J95: 162.4 | K95: 3690.7922 | L95: 599384.65 | M95: 14.449 | N95: 3690.7922 | O95: 53328.257 | P95: 1月 | X95: =W94-X94
B96: 带钢 | C96: 吨 | D96: 14.449 | E96: 3690.7924 | F96: 53328.26 | G96: 58.107 | H96: 3460.2019 | I96: 201061.95 | J96: 41.5 | K96: 3506.1223 | L96: 145504.08 | M96: 31.056 | N96: 3506.1223 | O96: 108886.13 | P96: 2月
B97: 镀锌卷板 | C97: 吨 | G97: 23.948 | H97: 3734.6772 | I97: 89438.05 | J97: 23.948 | K97: 3734.6772 | L97: 89438.05 | M97: 0 | N97: #DIV/0! | O97: 0 | P97: 2月
J102: =SUM(J93:J100) | K102: =L102/J102 | L102: =SUM(L93:L100)
G103: =K102*1.13 | J103: =J102*0.12 | K103: 2519.91 | L103: =J103*K103
G105: =K106/G103 | I105: 预测废料 | J105: =J83-U74+J103-U91 | K105: =L105/J105 | L105: =L84-Y74+L103-Y91
K106: =V91*1.13 | L106: =J105*K106
R109: 以上废料已结算
U111: 数量 | V111: 单价 | W111: 金额 | X111: 税额 | Y111: 含税金额
B112: 品名 | C112: 单位 | D112: 上月结存 | G112: 本月进仓数 | J112: 本月发出数 | M112: 本月结余 | P112: 备注 | R112: 2025.05.27 | S112: *金属制品*废铁 | T112: 吨 | U112: 41.767 | V112: =W112/U112 | W112: 89380.53 | X112: 11619.47 | Y112: =W112+X112
D113: 数量 | E113: 单价 | F113: 金额 | G113: 数量 | H113: 单价 | I113: 金额 | J113: 数量 | K113: 单价 | L113: 金额 | M113: 数量 | N113: 单价 | O113: 金额 | R113: 2025.09.24 | S113: *金属制品*废铁 | T113: 吨 | U113: 33.42 | V113: 2139.9797 | W113: 71518.12 | X113: 9297.36 | Y113: 80815.48
B114: 带钢 | C114: 吨 | D114: 31.056 | E114: 3506.1222 | F114: 108886.13 | G114: 101.234 | H114: 3596.7576 | I114: 364114.16 | J114: 68 | K114: 3575.4803 | L114: 243132.66 | M114: 64.29 | N114: 3575.4803 | O114: 229867.63 | P114: 3月 | R114: 2025.09.24 | S114: *金属制品*废铁 | T114: 吨 | U114: 30.435 | V114: 2139.9796 | W114: 65130.28 | X114: 8466.94 | Y114: 73597.22
B115: 镀锌卷板 | C115: 吨 | G115: 12.34 | H115: 3743.4919 | I115: 46194.69 | J115: 12.34 | K115: 3743.4919 | L115: 46194.69 | M115: 0 | N115: #DIV/0! | O115: 0 | P115: 3月
B116: 带钢 | C116: 吨 | D116: 64.29 | E116: 3575.4803 | F116: 229867.63 | G116: 122.304 | H116: 3482.3064 | I116: 425900 | J116: 152 | K116: 3514.409 | L116: 534190.17 | M116: 34.594 | N116: 3514.409 | O116: 121577.46 | P116: 4月
B117: 带钢 | C117: 吨 | D117: 34.594 | E117: 3514.4089 | F117: 121577.46 | G117: 48.189 | H117: 3783.5352 | I117: 182324.78 | J117: 41 | K117: 3671.0706 | L117: 150513.9 | M117: 41.783 | N117: 3671.0706 | O117: 153388.34 | P117: 5月
B118: 镀锌卷板 | C118: 吨 | G118: 24.566 | H118: 3656.3954 | I118: 89823.01 | J118: 24.566 | K118: 3656.3954 | L118: 89823.01 | M118: 0 | N118: #DIV/0! | O118: 0 | P118: 5月
B119: 带钢 | C119: 吨 | D119: 41.783 | E119: 3671.0705 | F119: 153388.34 | G119: 14.102 | H119: 3407.1614 | I119: 48047.79 | J119: 49.2 | K119: 3604.4758 | L119: 177340.21 | M119: 6.685 | N119: 3604.4758 | O119: 24095.921 | P119: 6月 | W119: =SUM(W112:W118)-W112 | X119: =W119*测算表!G25
B120: 镀锌卷板 | C120: 吨 | G120: 16.2 | H120: 3751.9395 | I120: 60781.42 | J120: 16.2 | K120: 3751.9395 | L120: 60781.42 | M120: 0 | N120: #DIV/0! | O120: 0 | P120: 6月 | X120: =W119-X119
B121: 冷轧卷板 | C121: 吨 | G121: 68.936 | H121: 3210.6219 | I121: 221327.43 | J121: 18.5 | K121: 3210.6219 | L121: 59396.505 | M121: 50.436 | N121: 3210.6219 | O121: 161930.93 | P121: 7月
B122: 带钢 | C122: 吨 | D122: 166.429 | E122: 3822.717 | F122: 636210.96 | G122: 35.005 | H122: 3394.2814 | I122: 118816.82 | J122: 112 | K122: 3748.2638 | L122: 419805.55 | M122: 89.434 | N122: 3748.2638 | O122: 335222.23 | P122: 8月
B123: 镀锌卷板 | C123: 吨 | G123: 12.48 | H123: 3460.3333 | I123: 43184.96 | J123: 12.48 | K123: 3460.3333 | L123: 43184.96 | M123: 0 | N123: #DIV/0! | O123: 0 | P123: 8月
B124: 冷轧卷板 | C124: 吨 | D124: 50.436 | E124: 3210.622 | F124: 161930.93 | J124: 50.436 | K124: 3210.622 | L124: 161930.93 | M124: 0 | N124: #DIV/0! | O124: 0 | P124: 8月
B125: 带钢 | C125: 吨 | D125: 89.434 | E125: 3748.2639 | F125: 335222.23 | G125: 98.505 | H125: 3404.6518 | I125: 335375.23 | J125: 152.7 | K125: 3568.1655 | L125: 544858.88 | M125: 35.239 | N125: 3568.1655 | O125: 125738.58 | P125: 9月
B126: 镀锌卷板 | C126: 吨 | G126: 14.06 | H126: 3540.3898 | I126: 49777.88 | J126: 14.06 | K126: 3540.3898 | L126: 49777.88 | M126: 0 | N126: #DIV/0! | O126: 0 | P126: 9月
B127: 带钢 | C127: 吨 | D127: 35.239 | E127: 3568.1654 | F127: 125738.58 | J127: 35.239 | K127: 3568.1654 | L127: 125738.58 | M127: 0 | N127: #DIV/0! | O127: 0 | P127: 10月
B128: 镀锌卷板 | C128: 吨 | G128: 24.177 | H128: 3637.0778 | I128: 87933.63 | J128: 24.177 | K128: 3637.0778 | L128: 87933.63 | M128: 0 | N128: #DIV/0! | O128: 0 | P128: 10月
B129: 冷轧带钢 | C129: 吨 | G129: 100.024 | H129: 3184.9879 | I129: 318575.23 | J129: 72.5 | K129: 3184.9879 | L129: 230911.62 | M129: 27.524 | N129: 3184.9879 | O129: 87663.607 | P129: 10月
B130: 带钢 | C130: 吨 | G130: 25.477 | H130: 3256.7983 | I130: 82973.45 | J130: 25.477 | K130: 3256.7983 | L130: 82973.45 | M130: 0 | N130: #DIV/0! | O130: 0 | P130: 11月
B131: 镀锌卷板 | C131: 吨 | G131: 8.508 | H131: 3681.3869 | I131: 31321.24 | J131: 8.508 | K131: 3681.3869 | L131: 31321.24 | M131: 0 | N131: #DIV/0! | O131: 0 | P131: 11月
B132: 冷轧带钢 | C132: 吨 | D132: 27.524 | E132: 3184.988 | F132: 87663.61 | G132: 80.754 | H132: 3287.5985 | I132: 265486.73 | J132: 108.278 | K132: 3261.5152 | L132: 353150.34 | M132: 0 | N132: #DIV/0! | O132: 0 | P132: 11月
B133: 冷轧板卷 | C133: 吨 | D133: 12.318 | E133: 3615.3296 | F133: 44533.63 | J133: 12.318 | K133: 3615.3296 | L133: 44533.63 | M133: 0 | N133: #DIV/0! | O133: 0 | P133: 11月
B134: 冷轧卷板 | C134: 吨 | D134: 105.346 | E134: 3165.4814 | F134: 333470.8 | G134: 41.671 | H134: 3187.6331 | I134: 132831.86 | J134: 69.5 | K134: 3171.7601 | L134: 220437.33 | M134: 77.517 | N134: 3171.7601 | O134: 245865.33 | P134: 11月
B135: 带钢 | C135: 吨 | G135: 32.43 | H135: 3469.1739 | I135: 112505.31 | J135: 32.43 | K135: 3469.1739 | L135: 112505.31 | M135: 0 | N135: #DIV/0! | O135: 0 | P135: 12月
B136: 冷轧带钢 | C136: 吨 | G136: 198.272 | H136: 3141.9964 | I136: 622969.91 | J136: 119.5 | K136: 3141.9964 | L136: 375468.57 | M136: 78.772 | N136: 3141.9964 | O136: 247501.34 | P136: 12月
B137: 冷轧卷板 | C137: 吨 | D137: 77.517 | E137: 3171.7601 | F137: 245865.33 | J137: 77.517 | K137: 3171.7601 | L137: 245865.33 | M137: 0 | N137: #DIV/0! | O137: 0 | P137: 12月
J140: =SUM(J114:J138) | K140: =L140/J140 | L140: =SUM(L114:L138)
G141: =K140*1.13 | J141: =J140*0.165 | K141: =V114*1.13 | L141: =J141*K141
...

Sheet 加工成本
A1: 揭阳市揭东区磐东洪运来机械厂
A2: 加工成本计算表
A3: 项 目 | B3: 数量 | C3: 单位 | D3: 单位成本 | E3: 合 计
A4: 工 资 | C4: 吨 | D4: 323
A5: 制造费用 | C5: 吨 | D5: 645 | E5: =E12*0.45149*0.954
A6: 总 计 | B6: =B4 | D6: 968 | E6: =E4+E5
A12: 加工收入： | E12: =E11/1.17
A14: 加工利润 | E14: =E12-E6
A16: 毛利率 | E16: =E14/E12
